kvk/License.txt
kvk/__init__.py
kvk/kvk.py
kvk-1.3.2.dist-info/METADATA
kvk-1.3.2.dist-info/WHEEL
kvk-1.3.2.dist-info/top_level.txt
kvk-1.3.2.dist-info/RECORD
