Metadata-Version: 2.1
Name: kvk
Version: 1.3.2
Summary: kvk file handler
Author: Cargo
License: UNKNOWN
Platform: UNKNOWN
